imhotep_bandit/__init__.py
imhotep_bandit/plugin.py
imhotep_bandit-0.1.1.dist-info/DESCRIPTION.rst
imhotep_bandit-0.1.1.dist-info/METADATA
imhotep_bandit-0.1.1.dist-info/RECORD
imhotep_bandit-0.1.1.dist-info/WHEEL
imhotep_bandit-0.1.1.dist-info/entry_points.txt
imhotep_bandit-0.1.1.dist-info/metadata.json
imhotep_bandit-0.1.1.dist-info/top_level.txt
